{"1":["天空|誓","启明星|和"],"2":["什么？|和","你|它使知道","什么？","启明星"],"3":["星","灿烂的"],"4":["不","每个","人的","除了","她|在","一个保护者"],"5":["他思考|应该|因此","世人","什么？|从","他被创造"],"6":["他被创造","从","水","被射出的"],"7":["它(水)出自","从","之间","脊柱的","胸肋的|和"],"8":["他(真主)|确实","在","他的|复原","大能的|必定"],"9":["日子","它被揭穿","众秘密"],"10":["没有|然后","他|为","从","力量","不|和","援助者"],"11":["天|誓","有的","云的"],"12":["大地|和","有的","缝的"],"13":["它(古兰)|确实","言辞|必定","辨真伪的"],"14":["不|和","它(古兰)","笑话|在"],"15":["他们|确实","他们用计谋","计谋"],"16":["我用计谋|和","计谋"],"17":["你应宽限|然后","不信道的人们","他们|你应宽限","稍微的"]}