{"1":["حٰمٓ."],"2":["(ھي) نازل ڪيل آھي","ٻاجھاري مھربان وٽان.","*","*"],"3":["(ھي) اھڙو ڪتاب آھي","جو کولي بيان ڪيون ويون آھن","ھن جون آيتون","قرآن آھي","عربي ٻوليءَ ۾","ان قوم لاءِ جيڪا","سمجھي ٿي."],"4":["خوشخبري ڏيندڙ","۽ خبردار ڪندڙ","پوءِ منھن موڙيو","انھن مان اڪثر","پوءِ اھي","نٿا","ٻڌن."],"5":["۽ ھنن چيو","اسان جون دليون","پردن ۾ آھن","*","انھيءَ کان","جو تون سڏين ٿو","ان ڏانھن","۽ اسان جي ڪنن ۾","*","ٻوچ (ٽاٽ) آھن","۽ اسان جي وچ ۾","*","۽ تنھنجي جي وچ ۾","ھڪ پردو آھي","پوءِ تون (پنھنجو) ڪم ڪر","بيشڪ اسان","(پنھنجو) ڪم ڪندڙ آھيون."],"6":["چئه (اي مُحَمَّد ؐ !)","بس","مان ته","ھڪ بشر ئي آھيان","توھان وانگر","وحي ڪئي وڃي ٿي","مون ڏانھن","اھا ته توھان جو معبود","*","ھڪ ئي معبود آھي","*","پوءِ سڌ اختيار ڪريو","انھيءَ ڏانھن","۽ کانئس بخشش گهرو.","۽ ويل آھي","مشرڪن لاءِ."],"7":["اُھي جيڪي","نٿا","ڏين","زڪوات","۽ اُھي","آخرت جو به","ھو","انڪار ڪندڙ آھن."],"8":["بيشڪ","اُھي جن","ايمان آندو","۽ عمل ڪيا","صالح","انھن لاءِ","اجر آھي","اڻ","کٽ."],"9":["چئه (اي مُحَمَّد ؐ !)","ڇا بيشڪ توھان","البت ڪفر ڪريو ٿا","انھيءَ ذات سان جنھن","خلقيو","زمين کي","ٻن ڏينھن ۾","*","۽ توھان بڻايو ٿا","انھيءَ لاءِ","شريڪ.","اُھو جھانن جو پالڻھار آھي.","*","*"],"10":["۽ ھن بڻايا","ان (زمين) ۾","مضبوط جبل","ان جي مٿان","*","۽ ھن جي برڪت رکي","ان ۾","۽ ھن اندازو رکيو","ان ۾","ان جي غذائن جو","(اھي سڀ ڪم) چئن ڏينھن ۾.","*","*","ھڪ جھڙو","(جواب ٿيو) پڇندڙن لاءِ."],"11":["وري","ھن ڌيان ڏنو","آسمان ڏانھن","*","جڏھن جو اھو","دونھون ھو","پوءِ ھن چيو","ان کي","۽ زمين کي","توھان ٻئي اچو","خوشيءَ سان","يا","نه گهرندي.","(ته) ٻنھي چيو","اسان آياسين","رضا (خوشيءَ) سان."],"12":["پوءِ ھن بڻايو انھن کي","ست","آسمان","ٻن ڏينھن ۾","*","۽ ھن القا ڪيو","ھرآسمان ۾","*","*","ان جو ڪم.","۽ اسان سينگاريو","دنيا جي آسمان کي","*","ڏيئن سان","۽ (ان جي خوب) حفاظت ڪئي.","اھو","اندازو آھي","زبردست","ڄاڻندڙ جو."],"13":["پوءِ جيڪڏھن","اُھي منھن موڙين","ته چئه","مون توھان کي ڊيڄاريو آھي","کنوڻ جي ڪڙڪاٽ کان","وانگر","کنوڻ","عاد ۽ ثمود جي.","*"],"14":["جڏھن","آيا انھن وٽ","رسول","انھن جي اڳيان کان","*","*","۽ سندن پويان کان","*","ته نه","عبادت ڪريو","سواءِ اللھ جي.","*","(ته) ھنن چيو","جيڪڏھن","گهري ھا","اسان جو ربّ","ته ضرور نازل ڪري ھا","ملائڪ","پوءِ بيشڪ اسان ته","ان شيءِ جو","توھان موڪليا ويا آھيو","انھيءَ سان","انڪار ڪندڙ آھيون."],"15":["پوءِ پر","عاد (وارا) آھن","پوءِ انھن تڪبر ڪيو","زمين ۾","*","ناحق","*","۽ چيائون","ڪير آھي","وڌيڪ ڏاڍو","اسان کان","طاقت ۾.","ڇا ناھي","انھن ڏٺو","ته بيشڪ","اللھ","جنھن","ھنن کي خلقيو","اھو","وڌيڪ ڏاڍو آھي","انھن کان","طاقت ۾.","۽ اھي ھئا","اسان جي آيتن جو","انڪار ڪندا."],"16":["پوءِ اسان موڪلي","انھن تي","ھوا","سخت","منحوس (ثابت ٿيڻ واري) ڏينھن ۾","*","*","ته جيئن کين چکايون","خواريءَ وارو عذاب","*","دنيا جي حياتيءَ ۾.","*","*","۽ البت آخرت جو عذاب","*","ڏاڍو خوار ڪندڙ آھي","۽ اھي","نه","مدد ڪيا ويندا."],"17":["۽ پر","(قوم) ثمود","پوءِ اسان کين رستو ڏيکاريو","پوءِ به انھن پسند ڪيو","انڌائپ کي","ھدايت تي","*","پوءِ ورتو کين","کنوڻ","خواريءَ جي عذاب جي","*","انھيءَ ڪري جو جيڪي","ھئا اھي","ڪمائيندا."],"18":["۽ اسان بچايو","انھن کي جن","ايمان آندو","۽ ھئا اھي","پرھيزگار."],"19":["۽ جنھن ڏينھن","گڏ ڪيو ويندو","اللھ جي دشمنن کي","*","باھ ڏانھن","*","ته اھي","روڪيا ويندا."],"20":["تان جو","جڏھن","اُھي ايندا ان وٽ","*","(ته) شاھدي ڏيندا","انھن تي","سندن ڪَنَ","۽ سندن اکيون","۽ سندن کلون","ساڻ انھن جي جيڪي","ھئا اھي","ڪندا."],"21":["۽ ھو چوندا","پنھنجن کلن کي","ڇو","توھان شاھدي ڏني","اسان تي؟","اھي چونديون","اسان کي ڳالھرايو","ان اللھ جنھن","*","ڳالھرايو","ھرشيءِ کي","*","۽ انھيءَ ئي خلقيو توھان کي","*","پھرين ڀيري","*","۽ انھيءَ ڏانھن ئي","توھان موٽايا ويندؤ."],"22":["۽ نه","توھان ھئا","پردو ڪندا","ان (خوف) کان ته","شاھدي ڏيندا","توھان تي","توھان جا ڪَنَ","۽ نه","توھان جون اکيون","۽ نه","توھان جو کلون","۽ پر","توھان گمان ڪيو","ته بيشڪ","اللھ","نٿو","ڄاڻي","گهڻن ئي","انھن کي جيڪي","توھان ڪندا ھئا."],"23":["۽ اھو","توھان جو گمان آھي","اھو جيڪو","توھان گمان ڪيو","پنھنجي ربّ بابت","انھيءَ ئي برباد ڪيو توھان کي","پوءِ ٿي پيا توھان","نقصان وارن مان.","*"],"24":["پوءِ جيڪڏھن","ھو صبر ڪن","ته باھ ئي","رھڻ جي جاءِ آھي","انھن لاءِ","۽ جيڪڏھن","ھو معافي گهرندا","ته نه ٿيندا","اُھي","معاف ڪيل ماڻھن مان.","*"],"25":["۽ اسان مقرر ڪيا","انھن لاءِ","ڪجھ (بڇڙا) ساٿي","پوءِ انھن سھڻو ڪري ڏيکاريو","انھن لاءِ","اھو جيڪو","سندن اڳيان ھو","*","۽ اھو جيڪي","سندن پٺيان ھو","۽ ثابت ٿي وئي","انھن تي","ڳالھ","انھن امتن سان جيڪي","*","تحقيق","ٿي گذريون","انھن کان اڳ","*","جنن ۽ انسانن مان","*","*","بيشڪ اھي","ھئا","نقصان وارن مان."],"26":["۽ چيو","انھن جن","ڪفر ڪيو","نه","توھان ٻُڌو","ھن قرآن کي","*","۽ گوڙ مچايو","ان (جي پڙھڻ جي وقت) ۾","ته جيئن توھان","غالب ٿيو."],"27":["پوءِ البت اسان ضرور چکائينداسين","انھن کي جن","ڪفر ڪيو","عذاب","شديد","۽ البت اسان ضرور کين بدلو ڏينداسين","انھن بڇڙن ڪمن جو جيڪي","*","ھئا اھي","ڪندا."],"28":["اھو","بدلو آھي","اللھ جي دشمنن جو","*","باھ،","انھن لاءِ","ان ۾","گهر آھي","ھميشه (رھڻ) جو.","بدلو","ان جو جيڪي","ھئا اھي","اسان جي آيتن جو","انڪار ڪندا."],"29":["۽ چوندا","اُھي جن","ڪفر ڪيو","اي اسان جا ربّ!","تون ڏيکار اسان کي","اھي ٻئي (ٽولا) جن","گمراھ ڪيو ھو اسان کي","جنن ۽ انسانن مان","*","*","اسان ڪريون انھن کي","ھيٺان","پنھنجن پيرن جي","ته جيئن اھي ھجن","سڀني کان ھيٺين مان.","*"],"30":["بيشڪ","اھي جن","چيو","اسان جو ربّ اللھ آھي","*","وري","ان تي ڄمي بيٺا","لھن ٿا","انھن تي","ملائڪ","ھي (چوندي) ته نه","توھان ڊڄو","۽ نه","غمگين ٿيو","۽ خوش ٿي وڃو","جنت سان","اھا جنھن جو","توھان ھئا","وعدو ڏنا ويندا."],"31":["اسان","توھان جا دوست آھيون","دنيا جي حياتيءَ ۾","*","*","۽ آخرت ۾ (به)","*","۽ توھان لاءِ آھي","ان ۾","جيڪي","گهرندا","توھان جا نفس","۽ توھان لاءِ آھي","ان ۾","جيڪي","توھان گهرندا."],"32":["ميزبانيءَ طور","بخشڻھار مھربان جي طرفان.","*","*"],"33":["۽ ڪير","وڌيڪ ڀلو آھي","ڳالھ جي لحاظ کان","ان کان جنھن","سڏيو","اللھ ڏانھن","*","۽ عمل ڪيائين","صالح","۽ چيائين","مان ته بيشڪ","فرمانبردارن مان آھيان.","*"],"34":["۽ ناھي","برابر ٿيندي","نيڪي","۽ نه","بدي.","تون ٽار (بديءَ کي)","اھڙيءَ ڳالھ سان جو","اُھا","ڀلي ھجي","پوءِ ھڪدم","اھو جو","تنھنجي وچ ۾ (اي مُحَمَّد ؐ !)","۽ ان جي وچ ۾","دشمني ھجي","(ائين ٿي پوندو) ڄن ته اھو","دوست آھي","ڏاڍو گھَرو."],"35":["۽ نٿي","ملائي (نصيب ڪرائي) وڃي (اھا خوبي)","پر","انھن کي جيڪي","صبر ڪن ٿا","۽ نٿي","سيکاري وڃي ھيءَ (خوبي)","سواءِ","ان جي جيڪو وڏو بختاور آھي.","*","*"],"36":["۽ جيڪڏھن","توکي اُڀاري (اي مُحَمَّد ؐ !)","شيطان طرفان","*","ڪوئي وسوسو","ته تون اللھ جي پناھ گهُر.","*","بيشڪ اھو ئي","*","خوب ٻڌندڙ","ڄاڻندڙ آھي."],"37":["۽ سندس نشانين مان آھي","*","رات","۽ ڏينھن","۽ سج","۽ چنڊ.","نه","توھان سجدو ڪريو","سج کي","۽ نه","چنڊ کي","۽ سجدو ڪريو","اللھ کي","جنھن","انھن سڀني کي خلقيو","جيڪڏھن","آھيو توھان","فقط انھيءَ جي ئي","عبادت ڪندا."],"38":["پوءِ جيڪڏھن","اُھي تڪبر ڪن","ته اُھي جيڪي","تنھنجي ربّ وٽ آھن","*","پاڪائي بيان ڪن ٿا","انھيءَ جي","رات جو","۽ ڏينھن جو","۽ اُھي","نٿا","ٿڪجن."],"39":["۽ انھيءَ (اللھ) جي نشانين مان آھي","*","ته بيشڪ تون (اي مُحَمَّد ؐ !) ڏسين ٿو","*","زمين کي","سڪل","پوءِ جڏھن","اسان وَسايو","انھيءَ تي","پاڻي","ته (سَلَن جي) سُر پُر واري ٿي پئي","۽ اُڀري نڪتي.","بيشڪ","اھو (اللھ) جنھن","ان (زمين) کي زنده ڪيو","البت جيئرو ڪرڻ وارو آھي","مُردن کي،.","بيشڪ ھو","ھرشيءِ تي","*","*","قادر آھي."],"40":["بيشڪ","اُھي جيڪي","ڏنگائي پيدا ڪن ٿا","اسان جي آيتن ۾","*","نٿا","اھي ڳجھا رھن","اسان تي.","ڇا پوءِ اھو جڪيو","وڌو ويندو","باھه ۾","*","بھتر آھي","يا","اھو جيڪو","ايندو","امن سان","قيامت جي ڏينھن؟","*","توھان عمل ڪريو","جيڪي","توھان کي وڻي","بيشڪ ھو (اللھ)","ساڻ ان جي جيڪي","توھان ڪريو ٿا","خوب ڏسندڙ آھي."],"41":["بيشڪ","اُھي جن","ڪفر ڪيو","قرآن سان","جڏھن","اھو وٽن آيو (ته اُھي برباد ٿيندا)","۽ بيشڪ اھو","البت ھڪ ڪتاب آھي","وڏيءَ عزت وار."],"42":["نٿو","اچي سگھي ان وٽ","باطل","ان جي اڳيان کان","*","*","۽ نه","ان جي پٺيان کان.","*","(اھو) نازل ڪيل آھي","وڏي داناءَ ساراھيل وٽان.","*","*"],"43":["نٿو","چيو وڃي","توکي(اي مُحَمَّد ؐ !)","پر","اھو جيڪو","تحقيق","چيو ويو","رسولن کي","توکان اڳ.","*","بيشڪ","تنھنجو ربّ","بخشيندڙ (به) آھي","*","۽ دردناڪ عذاب وارو (به).","*","*"],"44":["۽ جيڪڏھن","ڪريون ھا اسان ان کي","قرآن","عجمي ٻوليءَ ۾","ته البت اُھي چون ھا","ڇو نه","کولي بيان ڪيون ويون","ھن جون آيتون؟","ڇا (ڪتاب) عجمي آھي","۽ (رسول) عربي؟","چئه (اي مُحَمَّد ؐ !)","اھو","انھن لاءِ جن","ايمان آندو","ھدايت ۽ شفا آھي.","*","۽ اُھي جيڪي","نٿا","ايمان آڻين","انھن جي ڪنن ۾","*","ٻوچ آھي","۽ اھو","انھن لاءِ","انڌائپ آھي.","اھي ئي","(ڄڻ) سڏيا وڃن ٿا","پرانھين ھنڌ تان.","*","*"],"45":["۽ البت تحقيق","اسان ڏنو","موسيٰ کي","ڪتاب","پوءِ اختلاف ڪيو ويو","ان ۾.","۽ جيڪڏھن نه ھجي ھا","ھڪ ڳالھ","جيڪا اڳواٽ (مقرر) ٿيل ھئي","تنھنجي ربّ وٽان","*","ته ضرور فيصلو ڪيو وڃي ھا","انھن جي وچ ۾.","۽ بيشڪ اھي","البت شڪ ۾آھن","*","ان جي طرفان","جيڪو مونجھاري ۾ وجھندڙ آھي."],"46":["جنھن","عمل ڪيو","صالح","ته ان جي پنھنجي لاءِ ئي آھي","۽ جنھن","بدي ڪئي","ته ان تي ئي آھي (ان جو وبال).","۽ نه آھي","تنھنجو ربّ","ظلم ڪندڙ","ٻانھن تي."],"47":["انھيءَ ڏانھن ئي","موٽايو وڃي ٿو","علم","قيامت (جي اچڻ) جو،","۽ نٿو","نڪري","ڪوئي ميوو","*","پنھنجن پردن مان","*","۽ نٿي","ڳورھاري ٿئي","ڪائي مادي","*","۽ نه","(ڪو ڦر) ڄڻي ٿي","سواءِ","ھن جي علم جي.","۽ جنھن ڏينھن","ھو کين سڏيندو","ڪٿي آھن","منھنجا شريڪ","ھو چوندا","اسان توکي ٻڌائي چڪا آھيون،","نه آھي","اسان مان","ڪوئي","شاھد (ھن ڳالھ جو)."],"48":["۽ گم ٿي ويندا","انھن کان","اھي جن کي","ھئا اھي","سڏيندا","ھن کان اڳ","*","۽ ھو گمان ڪندا","(ته) نه","انھن لاءِ","ڪا ڀڄڻ جي واھ.","*"],"49":["نٿو","ٿڪجي","انسان","ڀلائي گهرڻ کان","*","*","۽ جيڪڏھن","کيس پھچي","تڪليف","ته (ٿئي ٿو) ڏاڍو مايوس","سخت نا اميد."],"50":["۽ البت جيڪڏھن","اسان کيس چکيايون","رحمت","پاڻ وٽان","ان تڪليف کان پوءِ جيڪا","*","*","کيس پھتي","ته پڪ ھو چوي ٿو","ھي ته","مون لاءِ آھي","۽ نٿو","مان گمان ڪريان","قيامت جي","قائم ٿيڻ جو","۽ البت جيڪڏھن","مان موٽايو ويس","پنھنجي رب ڏانھن","*","(ته) بيشڪ","مون لاءِ","ان وٽ","البت ڀلائي ئي ھوندي","پوءِ البت اسان ضرور ٻڌائينداسين","انھن کي جن","ڪفر ڪيو","ان سان جيڪي","ھنن ڪيو","۽ البت اسان ضرور چکائينداسين کين","سخت عذاب.","*","*"],"51":["۽ جڏھن","اسان احسان ڪريون ٿا","اسان تي.","*","(ته) ھو منھن موڙي ٿو","۽ پري ٿي وڃي ٿو","پنھنجن پاسن ڀر","۽ جڏھن","کيس پھچي ٿي","تڪليف","ته دعائون گهرندڙ ٿئي ٿو","*","ڊگهيون ڊگھيون."],"52":["چئه (اي مُحَمَّد ؐ !)","ڀلا ڏسو ته","جيڪڏھن","ھجي اھو (قرآن)","اللھ جي طرفان","*","*","وري توھان انڪار ڪريو","*","ان جو","(ته) ڪير","وڌيڪ گمراھه آھي","ان کان","(ته) اھو","پر انھين مخالفت ۾آھي؟","*","*"],"53":["سگھوئي اسان کين ڏيکارينداسين","پنھنجيون نشانيون","ڪائنات ۾","*","۽ سندن نفسن ۾","*","تان جو","پڌرو ٿي ويندو","انھن لاءِ","ته بيشڪ اھو","(قرآن) حق آھي.","ڇا نه آھي","ڪافي","تنھنجو ربّ","(ھن ڳالھ تي) ته بيشڪ اھو","ھرشيءِ تي","*","*","شاھد آھي."],"54":["خبردار!","بيشڪ اھي","شڪ ۾ آھن","پنھنجي ربّ جي ملاقات کان.","*","*","*","خبردار!","بيشڪ اھو","ھرشيءِ کي","*","گهيرو ڪندڙ آھي."]}