{"1":["Quand","tremble","la terre","(avec) un tremblement"],"2":["et fait sortir","la terre","ses fardeaux"],"3":["et dit","l'humain :","\"Qu'est-ce-qu'","(il y a) à elle ?\""],"4":["Ce jour-là","elle racontera","ses information"],"5":["parce que","ton Maître","a inspiré","à elle."],"6":["Ce jour-là","iront","les gens","(en étant) séparés","afin qu'ils soient montrés","leurs actions."],"7":["Quiconque donc","a œuvré","le poids","(d')une chose la plus petite","(en) bien,","le verra,"],"8":["Et quiconque","a œuvré","le poids","(d')une chose la plus petite","(en) mal,","le verra."]}